indicasr/__init__.py
indicasr/indicasr.py
indicasr/spellcorrection.py
indicasr-1.0.0.dist-info/LICENSE
indicasr-1.0.0.dist-info/METADATA
indicasr-1.0.0.dist-info/WHEEL
indicasr-1.0.0.dist-info/top_level.txt
indicasr-1.0.0.dist-info/RECORD
