Metadata-Version: 2.1
Name: indicasr
Version: 1.0.0
Summary: Speeech Recognition for Indic languages.
Home-page: https://github.com/notAI-tech/IndicASR
Author: BEDAPUDI PRANEETH
Author-email: praneeth@bpraneeth.com
License: GPLv3
Platform: UNKNOWN
Classifier: License :: OSI Approved :: GNU General Public License v3 (GPLv3)
Classifier: Programming Language :: Python
Classifier: Programming Language :: Python :: 3
Classifier: Programming Language :: Python :: 3.6
Classifier: Programming Language :: Python :: Implementation :: CPython
Classifier: Programming Language :: Python :: Implementation :: PyPy
Requires-Python: >=3.6.0
Requires-Dist: transformers (>=4.4.2)
Requires-Dist: pydload (>=1.0.9)
Requires-Dist: torch
Requires-Dist: torchaudio
